flextabs/__init__.py
flextabs/__main__.py
flextabs/enums.py
flextabs/flextabs_demo.py
flextabs/openers.py
flextabs/tab_base.py
flextabs/tab_manager.py
flextabs/widgets.py
flextabs-0.2.0.dist-info/licenses/LICENSE
tests/__init__.py
tests/test_manager.py
flextabs-0.2.0.dist-info/METADATA
flextabs-0.2.0.dist-info/WHEEL
flextabs-0.2.0.dist-info/top_level.txt
flextabs-0.2.0.dist-info/RECORD
