Metadata-Version: 2.4
Name: flextabs
Version: 0.2.0
Summary: A flexible and extensible tab manager widget for tkinter applications built on top of ttk.Notebook
Home-page: https://github.com/MS-32154/flextabs
Author: MS-32154
Author-email: MS-32154 <msttoffg@gmail.com>
License-Expression: MIT
Project-URL: Homepage, https://github.com/MS-32154/flextabs
Project-URL: Bug Reports, https://github.com/MS-32154/flextabs/issues
Project-URL: Source, https://github.com/MS-32154/flextabs
Keywords: tkinter,ttk,Notebook,tabs,gui,widget,interface
Requires-Python: >=3.8
License-File: LICENSE
Requires-Dist: Pillow
Dynamic: author
Dynamic: home-page
Dynamic: license-file
Dynamic: requires-python
